text_diff_engine/__init__.py
text_diff_engine/diff_engine.py
text_diff_engine-3.0.1.dist-info/licenses/LICENSE
text_diff_engine-3.0.1.dist-info/METADATA
text_diff_engine-3.0.1.dist-info/WHEEL
text_diff_engine-3.0.1.dist-info/top_level.txt
text_diff_engine-3.0.1.dist-info/RECORD
