Metadata-Version: 2.4
Name: text_diff_engine
Version: 3.0.1
Summary: A Python wrapper for the Text Diff Engine with block moves API
Home-page: https://www.formamind.com/en/diffEngine
Author: Franciszek Łąjszczak
Author-email: franciszek@formamind.com
Classifier: Programming Language :: Python :: 3
Classifier: License :: OSI Approved :: MIT License
Classifier: Operating System :: OS Independent
Requires-Python: >=3.6
License-File: LICENSE
Requires-Dist: requests>=2.25.0
Dynamic: author
Dynamic: author-email
Dynamic: classifier
Dynamic: description
Dynamic: description-content-type
Dynamic: home-page
Dynamic: license-file
Dynamic: requires-dist
Dynamic: requires-python
Dynamic: summary
